{
  "facility": {
    "id": "open-ice",
    "name": "Open Ice (Public & Shinny)"
  },
  "weeks": [
    {
      "sunday": "2026-06-14",
      "file": "2026-06-14.json",
      "is_current": false
    },
    {
      "sunday": "2026-06-21",
      "file": "2026-06-21.json",
      "is_current": false
    },
    {
      "sunday": "2026-06-28",
      "file": "2026-06-28.json",
      "is_current": true
    },
    {
      "sunday": "2026-07-05",
      "file": "2026-07-05.json",
      "is_current": false
    },
    {
      "sunday": "2026-07-12",
      "file": "2026-07-12.json",
      "is_current": false
    }
  ]
}